pubchem_requests_python/__init__.py
pubchem_requests_python/compound.py
pubchem_requests_python/individual_property_requests.py
pubchem_requests_python-0.0.4.dist-info/licenses/LICENSE
pubchem_requests_python-0.0.4.dist-info/METADATA
pubchem_requests_python-0.0.4.dist-info/WHEEL
pubchem_requests_python-0.0.4.dist-info/top_level.txt
pubchem_requests_python-0.0.4.dist-info/RECORD
