Metadata-Version: 2.4
Name: pubchem-requests-python
Version: 0.0.4
Summary: A wrapper for the pubchem PUG REST API that simplifies retrieval of chemical information.
Author-email: Henry Nitzberg <henrynitzberg@gmail.com>
License-Expression: MIT
Project-URL: Homepage, https://github.com/henrynitzberg/pubchem_requests_python
Classifier: Programming Language :: Python :: 3
Classifier: Operating System :: OS Independent
Requires-Python: >=3.7
License-File: LICENSE
Requires-Dist: python-stdnum
Requires-Dist: requests
Requires-Dist: pytest
Dynamic: license-file
